pyocd_wireless/__init__.py
pyocd_wireless/__main__.py
pyocd_wireless/pyocd_wireless.py
pyocd_wireless-0.0.1.dist-info/DESCRIPTION.rst
pyocd_wireless-0.0.1.dist-info/METADATA
pyocd_wireless-0.0.1.dist-info/RECORD
pyocd_wireless-0.0.1.dist-info/WHEEL
pyocd_wireless-0.0.1.dist-info/entry_points.txt
pyocd_wireless-0.0.1.dist-info/metadata.json
pyocd_wireless-0.0.1.dist-info/top_level.txt
pyocd_wireless-0.0.1.dist-info/zip-safe
