Metadata-Version: 2.0
Name: pyocd-wireless
Version: 0.0.1
Summary: A wireless programming and debugging tool based on pyocd
Home-page: https://github.com/makerdiary/pyocd-wireless
Author: Yihui Xiong
Author-email: yihui.xiong@hotmail.com
License: UNKNOWN
Platform: UNKNOWN
Requires-Dist: bleak
Requires-Dist: pyocd
